cdktf_cdktf_provider_waypoint/__init__.py
cdktf_cdktf_provider_waypoint/py.typed
cdktf_cdktf_provider_waypoint/_jsii/__init__.py
cdktf_cdktf_provider_waypoint/_jsii/provider-waypoint@3.0.1.jsii.tgz
cdktf_cdktf_provider_waypoint/auth_method/__init__.py
cdktf_cdktf_provider_waypoint/config_source/__init__.py
cdktf_cdktf_provider_waypoint/data_waypoint_app/__init__.py
cdktf_cdktf_provider_waypoint/data_waypoint_auth_method/__init__.py
cdktf_cdktf_provider_waypoint/data_waypoint_project/__init__.py
cdktf_cdktf_provider_waypoint/data_waypoint_runner_profile/__init__.py
cdktf_cdktf_provider_waypoint/project/__init__.py
cdktf_cdktf_provider_waypoint/provider/__init__.py
cdktf_cdktf_provider_waypoint/runner_profile/__init__.py
cdktf_cdktf_provider_waypoint-3.0.1.dist-info/LICENSE
cdktf_cdktf_provider_waypoint-3.0.1.dist-info/METADATA
cdktf_cdktf_provider_waypoint-3.0.1.dist-info/WHEEL
cdktf_cdktf_provider_waypoint-3.0.1.dist-info/top_level.txt
cdktf_cdktf_provider_waypoint-3.0.1.dist-info/RECORD
